corona_chan_gob_mx/__init__.py
corona_chan_gob_mx/scraper.py
corona_chan_gob_mx-1.0.0.dist-info/AUTHORS.rst
corona_chan_gob_mx-1.0.0.dist-info/LICENSE
corona_chan_gob_mx-1.0.0.dist-info/METADATA
corona_chan_gob_mx-1.0.0.dist-info/WHEEL
corona_chan_gob_mx-1.0.0.dist-info/entry_points.txt
corona_chan_gob_mx-1.0.0.dist-info/top_level.txt
corona_chan_gob_mx-1.0.0.dist-info/RECORD
