Metadata-Version: 2.1
Name: corona-chan-gob-mx
Version: 1.0.0
Summary: corona chan scraper for gob mx
Home-page: https://github.com/dem4ply/corona_chan_gob_mx
Author: dem4ply
Author-email: dem4ply@gmail.com
License: WTFPL
Keywords: corona_chan_gob_mx
Platform: UNKNOWN
Classifier: Development Status :: 2 - Pre-Alpha
Classifier: Intended Audience :: Developers
Classifier: License :: Public Domain
Classifier: Natural Language :: English
Classifier: Programming Language :: Python :: 3.7
Classifier: Programming Language :: Python :: 3.8
Requires-Dist: chibi-requests (>=0.3.3)
Requires-Dist: PyPDF2 (>=1.26.0)
Requires-Dist: camelot-py[cv] (>=0.7.3)
